ommlds/.omlish-manifests.json
ommlds/README.md
ommlds/__about__.py
ommlds/__init__.py
ommlds/_hacks/__init__.py
ommlds/_hacks/funcs.py
ommlds/_hacks/names.py
ommlds/_hacks/params.py
ommlds/_hacks/patches.py
ommlds/backends/__init__.py
ommlds/backends/anthropic/__init__.py
ommlds/backends/anthropic/protocol/__init__.py
ommlds/backends/anthropic/protocol/_dataclasses.py
ommlds/backends/anthropic/protocol/_marshal.py
ommlds/backends/anthropic/protocol/types.py
ommlds/backends/anthropic/protocol/sse/__init__.py
ommlds/backends/anthropic/protocol/sse/_marshal.py
ommlds/backends/anthropic/protocol/sse/assemble.py
ommlds/backends/anthropic/protocol/sse/events.py
ommlds/backends/cerebras/__init__.py
ommlds/backends/cerebras/_dataclasses.py
ommlds/backends/cerebras/_marshal.py
ommlds/backends/cerebras/clients.py
ommlds/backends/cerebras/protocol.py
ommlds/backends/google/__init__.py
ommlds/backends/google/protocol/__init__.py
ommlds/backends/google/protocol/_dataclasses.py
ommlds/backends/google/protocol/_marshal.py
ommlds/backends/google/protocol/types.py
ommlds/backends/groq/__init__.py
ommlds/backends/groq/_dataclasses.py
ommlds/backends/groq/_marshal.py
ommlds/backends/groq/clients.py
ommlds/backends/groq/protocol.py
ommlds/backends/huggingface/__init__.py
ommlds/backends/huggingface/cache.py
ommlds/backends/huggingface/cli.py
ommlds/backends/llamacpp/__init__.py
ommlds/backends/llamacpp/buildwheel.py
ommlds/backends/llamacpp/logging.py
ommlds/backends/mlx/__init__.py
ommlds/backends/mlx/__main__.py
ommlds/backends/mlx/caching.py
ommlds/backends/mlx/cli.py
ommlds/backends/mlx/generation.py
ommlds/backends/mlx/limits.py
ommlds/backends/mlx/loading.py
ommlds/backends/mlx/tokenization/LICENSE
ommlds/backends/mlx/tokenization/__init__.py
ommlds/backends/mlx/tokenization/loading.py
ommlds/backends/mlx/tokenization/tokenization.py
ommlds/backends/mlx/tokenization/types.py
ommlds/backends/mlx/tokenization/detokenization/__init__.py
ommlds-0.0.0.dev516.dist-info/licenses/LICENSE
ommlds-0.0.0.dev516.dist-info/METADATA
ommlds-0.0.0.dev516.dist-info/WHEEL
ommlds-0.0.0.dev516.dist-info/entry_points.txt
ommlds-0.0.0.dev516.dist-info/top_level.txt
ommlds-0.0.0.dev516.dist-info/RECORD
